[
  {
    "id": "2e1f18be-73c7-8016-8bdb-d9310bb47954",
    "nom": "Boubinette",
    "age": 11,
    "sexe": "Femelle",
    "statut": "disponible",
    "description": "Boubinette, 11 ans, très câline, pas un brin d’agressivité mais du caractère. Elle est en bonne santé, stérilisée et identifiée par puce électronique.\n\nVoilà son histoire : elle a vécu 11 ans avec sa maitresse, elle vivait beaucoup dehors, avait un accès au sous-sol de la maison par une chatière mais passait le plus clair de son temps à l’extérieur.\n\nEn juin, sa maitresse est malheureusement partie en ehpad. Nous avons confié Boubinette à une gentille famille d’accueil, mais le chat de la maison n’était pas d’accord et l’entente entre les deux laissait à désirer. Boubinette s’est enfuie et n’a été retrouvée qu’un mois et demi plus tard.\n\nNous l’avons donc confiée à une autre famille d’accueil mais en appartement et cette petite minette a eu des épisodes de malpropreté, deux pipis sur le canapé et un sur le lit donc la famille d’accueil à jeté l’éponge.\n\nAlors nous lui cherchons une famille d’adoption. Idéalement une famille calme avec un extérieur accessible par chatière et pas d’autre animal. Elle est vraiment adorable et vous ne regretterez pas de lui donner sa chance.",
    "photo": [
      "images/adoptions/2e1f18be-73c7-8016-8bdb-d9310bb47954-0.jpg"
    ],
    "rescueDate": "2025-11-19",
    "url": "https://www.fonds-saint-bernard.com/adopter/chats-a-l-adoption/10-chat/72592-boubinette"
  },
  {
    "id": "2e1f18be-73c7-80ac-a07c-f1bd6d193889",
    "nom": "Ziggy",
    "sexe": "Mâle",
    "statut": "disponible",
    "description": "ZIGGY a 5 mois, c'est un grand au cœur tendre, lorsqu'il est en confiance il se laisse câliner avec plaisir et se met à ronronner.\n\nIl est identifié, vermifugé, déparasité et stérilisé.\n\nNous souhaitons une adoption double avec son frère Milos, ils sont très complices.",
    "photo": [
      "images/adoptions/2e1f18be-73c7-80ac-a07c-f1bd6d193889-0.jpg"
    ],
    "rescueDate": "2025-10-08",
    "url": "https://www.fonds-saint-bernard.com/adopter/chats-a-l-adoption/10-chat/70790-ziggy"
  },
  {
    "id": "2e1f18be-73c7-80d3-880d-e902a31be7c1",
    "nom": "Milos",
    "sexe": "Mâle",
    "statut": "disponible",
    "description": "MILOS est un beau chaton de 6 mois,  très joueur avec ses frères, lorsqu'il est en confiance il est très câlin.\n\nIl est stérilisé, vermifugé, déparasité et identifié par puce électronique.\n\nNous aimerions qu'il soit adopté avec son frère Ziggy ils sont très complices.",
    "photo": [
      "images/adoptions/2e1f18be-73c7-80d3-880d-e902a31be7c1-0.jpg"
    ],
    "rescueDate": "2025-10-21",
    "url": "https://www.fonds-saint-bernard.com/adopter/chats-a-l-adoption/10-chat/71373-milos"
  },
  {
    "id": "2e1f18be-73c7-80e5-8e4b-f9e720093e20",
    "nom": "Moncheri",
    "sexe": "Mâle",
    "statut": "disponible",
    "description": "MONCHERI est un adorable chaton de 7 mois encore timide. Il est identifié par puce électronique, déparasité, vermifugé et stérilisé.\n\nIl est très complice avec son frère Zéphyr, qui le pousse a sortir de sa coquille, c'est pour cela que nous souhaitons une adoption double.",
    "photo": [
      "images/adoptions/2e1f18be-73c7-80e5-8e4b-f9e720093e20-0.jpg"
    ],
    "rescueDate": "2025-12-15",
    "url": "https://www.fonds-saint-bernard.com/adopter/chats-a-l-adoption/10-chat/73468-moncheri"
  },
  {
    "id": "2e1f18be-73c7-80f2-b440-c5061cb6364c",
    "nom": "Zephir",
    "sexe": "Mâle",
    "statut": "disponible",
    "description": "ZEPHYR est un adorable chaton de 7 mois très câlin lorsqu'il est en confiance. Il est identifié par puce électronique, déparasité, vermifugé et stérilisé.\n\nIl est très complice avec son frère Monchéri, un peu plus timide, et nous souhaitons une adoption double.",
    "photo": [
      "images/adoptions/2e1f18be-73c7-80f2-b440-c5061cb6364c-0.jpg"
    ],
    "rescueDate": "2025-12-15",
    "url": "https://www.fonds-saint-bernard.com/adopter/chats-a-l-adoption/10-chat/73467-zephir"
  },
  {
    "id": "2d2f18be-73c7-8177-b4cf-deb237ee2e4a",
    "nom": "Nyouki",
    "age": 1,
    "sexe": "Mâle",
    "statut": "réservé",
    "description": "C’est Nyouki le plus beau",
    "photo": [
      "images/adoptions/2d2f18be-73c7-8177-b4cf-deb237ee2e4a-0.jpeg",
      "images/adoptions/2d2f18be-73c7-8177-b4cf-deb237ee2e4a-1.jpeg"
    ],
    "rescueDate": "2025-07-09"
  },
  {
    "id": "2d7f18be-73c7-8119-9245-fcc31a3f2845",
    "nom": "Perlouille",
    "sexe": "Femelle",
    "statut": "réservé",
    "description": "La méga super mimi perlouille ",
    "photo": [
      "images/adoptions/2d7f18be-73c7-8119-9245-fcc31a3f2845-0.jpeg"
    ],
    "rescueDate": "2026-01-07"
  },
  {
    "id": "2dcf18be-73c7-8006-bbf0-e5a30e7a8b63",
    "nom": "Poticha",
    "age": 23,
    "statut": "disponible",
    "maladie": "Coryza",
    "description": "C’est un poticha",
    "photo": [
      "/images/placeholder.png"
    ],
    "rescueDate": "2025-06-18"
  },
  {
    "id": "2dcf18be-73c7-806c-8d13-ebe31ce4f55d",
    "nom": "PPT",
    "age": 15,
    "sexe": "Femelle",
    "statut": "adopté",
    "maladie": "FIV",
    "description": "Future cosmonaute à ses heures pas si perdues",
    "photo": [
      "images/adoptions/2dcf18be-73c7-806c-8d13-ebe31ce4f55d-0.jpeg"
    ],
    "rescueDate": "2012-07-05"
  },
  {
    "id": "2def18be-73c7-81d6-86e9-eb890c1da176",
    "nom": "Chaussette",
    "sexe": "Femelle",
    "statut": "disponible",
    "description": "C'est chaussette",
    "photo": [
      "images/adoptions/2def18be-73c7-81d6-86e9-eb890c1da176-0.jpeg"
    ],
    "rescueDate": "2020-11-27"
  }
]